MANIFEST.in
README.rst
setup.cfg
setup.py
docs/genindex.html
docs/index.html
docs/py-modindex.html
docs/search.html
docs/searchindex.js
docs/_sources/index.txt
docs/_sources/rst/auto.txt
docs/_sources/rst/intro.txt
docs/_sources/rst/lib/obfuscator.txt
docs/_sources/rst/lib/obfuscator/file.txt
docs/_static/ajax-loader.gif
docs/_static/basic.css
docs/_static/comment-bright.png
docs/_static/comment-close.png
docs/_static/comment.png
docs/_static/default.css
docs/_static/doctools.js
docs/_static/down-pressed.png
docs/_static/down.png
docs/_static/file.png
docs/_static/jquery.js
docs/_static/minus.png
docs/_static/plus.png
docs/_static/pygments.css
docs/_static/searchtools.js
docs/_static/sidebar.js
docs/_static/underscore.js
docs/_static/up-pressed.png
docs/_static/up.png
docs/_static/websupport.js
docs/rst/auto.html
docs/rst/intro.html
docs/rst/lib/obfuscator.html
docs/rst/lib/obfuscator/file.html
obfuscator/__init__.py
obfuscator/file.py
obfuscator.egg-info/PKG-INFO
obfuscator.egg-info/SOURCES.txt
obfuscator.egg-info/dependency_links.txt
obfuscator.egg-info/top_level.txt
obfuscator.egg-info/zip-safe
tests/__init__.py
tests/test_obfuscator.py
tests/test_obfuscator_file.py