Metadata-Version: 1.1
Name: obfuscator
Version: 1.1.5
Summary: Data obfuscator package
Home-page: https://github.com/mtik00/obfuscator
Author: Timothy McFadden
Author-email: UNKNOWN
License: UNKNOWN
Download-URL: https://github.com/mtik00/obfuscator/releases/download/v1.1.5/obfuscator-1.1.5.tar.gz
Platform: UNKNOWN
Classifier: Development Status :: 5 - Production/Stable
Classifier: Environment :: Other Environment
Classifier: License :: OSI Approved :: GNU General Public License v2 (GPLv2)
Classifier: Programming Language :: Python
Classifier: Programming Language :: Python :: 2
Classifier: Programming Language :: Python :: 2.7
Classifier: Programming Language :: Python :: 3
Classifier: Intended Audience :: Developers
Classifier: Environment :: Console
Classifier: Natural Language :: English
Classifier: Operating System :: OS Independent
Classifier: Topic :: Security
